harina/__init__.py
harina/cli.py
harina/core.py
harina/utils.py
harina_v3_cli-3.1.0.dist-info/licenses/LICENSE
harina_v3_cli-3.1.0.dist-info/METADATA
harina_v3_cli-3.1.0.dist-info/WHEEL
harina_v3_cli-3.1.0.dist-info/entry_points.txt
harina_v3_cli-3.1.0.dist-info/top_level.txt
harina_v3_cli-3.1.0.dist-info/RECORD
