Metadata-Version: 2.4
Name: harina-v3-cli
Version: 3.1.0
Summary: CLI tool to recognize receipt images using Gemini API and output in XML format
Author-email: Developer <developer@example.com>
License: MIT
Project-URL: Homepage, https://github.com/example/harina-v3-cli
Project-URL: Repository, https://github.com/example/harina-v3-cli
Requires-Python: >=3.8
License-File: LICENSE
Requires-Dist: litellm>=1.0.0
Requires-Dist: click>=8.0.0
Requires-Dist: pillow>=9.0.0
Requires-Dist: requests>=2.28.0
Requires-Dist: python-dotenv>=1.0.0
Requires-Dist: google-cloud-aiplatform>=1.0.0
Requires-Dist: google-auth>=2.0.0
Requires-Dist: loguru>=0.7.0
Requires-Dist: sourcesage>=5.0.0
Requires-Dist: tqdm>=4.60.0
Dynamic: license-file
